AUTHORS
CHANGELOG.md
LICENSE
MANIFEST.in
README.md
setup.cfg
setup.py
adaptest/__init__.py
adaptest/__main__.py
adaptest/defaults.yml
adaptest/tools.py
adaptest.egg-info/PKG-INFO
adaptest.egg-info/SOURCES.txt
adaptest.egg-info/dependency_links.txt
adaptest.egg-info/entry_points.txt
adaptest.egg-info/not-zip-safe
adaptest.egg-info/requires.txt
adaptest.egg-info/top_level.txt
adaptest/templates/sequence.htt
examples/example1.htt
examples/example1.yml
tests/__init__.py
tests/__init__.pyc
tests/render1.txt
tests/render1.yml
tests/render2.txt
tests/render2.yml
tests/test_render.py
tests/__pycache__/test_render.cpython-27-PYTEST.pyc
tests/own/render2.txt
tests/own/render2.yml