Metadata-Version: 1.0
Name: adaptest
Version: 0.0.2
Summary: Adaptest - a lightweight YAML wrapper for httest
Home-page: https://github.com/Edke/adaptest
Author: Eduard Kracmar
Author-email: eduard@adaptiware.com
License: UNKNOWN
Platform: UNKNOWN
